LICENSE
MANIFEST.in
README.md
setup.py
hookman/__init__.py
hookman/manage.py
hookman.egg-info/PKG-INFO
hookman.egg-info/SOURCES.txt
hookman.egg-info/dependency_links.txt
hookman.egg-info/entry_points.txt
hookman.egg-info/requires.txt
hookman.egg-info/top_level.txt
hookman/hookman/__init__.py
hookman/hookman/args_manage.py
hookman/hookman/settings.py
hookman/hookman/webs/__init__.py
hookman/hookman/webs/event_tasks.py
hookman/hookman/webs/weblistener.py
tests/running_tests/__init__.py
tests/running_tests/test_config_setting.py
tests/running_tests/test_envents.py
tests/running_tests/test_run.py
tests/running_tests/test_run_and_stop.py
tests/web_tests/__init__.py
tests/web_tests/test_weblistener_basic.py
tests/web_tests/test_weblistener_events.py