Metadata-Version: 1.0
Name: hookman
Version: 0.1.2
Summary: this is a easy webhook manage tool for github webhook, developed by TDD
Home-page: https://github.com/mrzhangboss/hookman
Author: zhanglun
Author-email: zhanglun.me@gmail.com
License: Apache
Keywords: webhook github tool
Platform: UNKNOWN
